{"nome": " lavra", "extencao_do_arquivo": "CSV", "tabelas": [{"nome": " hegemonia", "campos": [{"nome": " disruptivo", "tipo": "float", "permite_nulo": true}, {"nome": " vigente", "tipo": "datetime", "permite_nulo": true}, {"nome": " beata", "tipo": "datetime", "permite_nulo": true}, {"nome": " resignado", "tipo": "bool", "permite_nulo": false}, {"nome": " dar", "tipo": "bool", "permite_nulo": true}, {"nome": " concomitante", "tipo": "bool", "permite_nulo": true}, {"nome": " sucumbir", "tipo": "datetime", "permite_nulo": true}, {"nome": " aleat\u00f3rio", "tipo": "datetime", "permite_nulo": false}, {"nome": " xilema", "tipo": "datetime", "permite_nulo": false}, {"nome": " disciplina", "tipo": "int", "permite_nulo": false}]}]}